README.md
setup.py
michelson_kernel/__init__.py
michelson_kernel/__main__.py
michelson_kernel/docs.py
michelson_kernel/kernel.js
michelson_kernel/kernel.py
michelson_kernel.egg-info/PKG-INFO
michelson_kernel.egg-info/SOURCES.txt
michelson_kernel.egg-info/dependency_links.txt
michelson_kernel.egg-info/requires.txt
michelson_kernel.egg-info/top_level.txt