Metadata-Version: 2.1
Name: michelson-kernel
Version: 0.1.6
Summary: Jupyter kernel for the Michelson language
Home-page: https://github.com/baking-bad/michelson-kernel
Author: Michael Zaikin (Baking Bad)
Author-email: mz@baking-bad.org
License: MIT
Keywords: Tezos,Michelson,Jupyter
Platform: UNKNOWN
Classifier: Intended Audience :: Developers
Classifier: Topic :: System :: Shells
Classifier: Framework :: IPython
Classifier: License :: OSI Approved :: MIT License
Classifier: Programming Language :: Python :: 3
